eyja_rethinkdb/__init__.py
eyja_rethinkdb/client.py
eyja_rethinkdb/config.py
tests/__init__.py
tests/test_client.py
eyja_rethinkdb-0.2.1.dist-info/METADATA
eyja_rethinkdb-0.2.1.dist-info/WHEEL
eyja_rethinkdb-0.2.1.dist-info/top_level.txt
eyja_rethinkdb-0.2.1.dist-info/zip-safe
eyja_rethinkdb-0.2.1.dist-info/RECORD
