Metadata-Version: 2.1
Name: eyja-rethinkdb
Version: 0.2.1
Summary: RethinkDB Plugin for Eyja
Home-page: https://gitlab.com/public.eyja.dev/eyja-rethinkdb
Maintainer: Anton Berdnikov
Maintainer-email: agratoth@yandex.ru
License: UNKNOWN
Platform: UNKNOWN
Classifier: License :: OSI Approved :: MIT License
Classifier: Operating System :: OS Independent
Classifier: Programming Language :: Python
Classifier: Programming Language :: Python :: 3.8
Classifier: Programming Language :: Python :: 3.9
Requires-Python: >=3.8
Requires-Dist: eyja-internal (>==0.4.5)
Requires-Dist: rethinkdb (>=2.4.8)
